ramodels/__init__.py
ramodels/base.py
ramodels/exceptions.py
ramodels/lora/__init__.py
ramodels/lora/_shared.py
ramodels/lora/facet.py
ramodels/lora/itsystem.py
ramodels/lora/klasse.py
ramodels/lora/organisation.py
ramodels/mo/__init__.py
ramodels/mo/_shared.py
ramodels/mo/class_.py
ramodels/mo/detail.py
ramodels/mo/details/__init__.py
ramodels/mo/details/_shared.py
ramodels/mo/details/address.py
ramodels/mo/details/association.py
ramodels/mo/details/engagement.py
ramodels/mo/details/it_system.py
ramodels/mo/details/kle.py
ramodels/mo/details/leave.py
ramodels/mo/details/manager.py
ramodels/mo/details/owner.py
ramodels/mo/details/related_unit.py
ramodels/mo/details/role.py
ramodels/mo/employee.py
ramodels/mo/facet.py
ramodels/mo/organisation.py
ramodels/mo/organisation_unit.py
ramodels/py.typed
ramodels-50.3.0.dist-info/WHEEL
ramodels-50.3.0.dist-info/entry_points.txt
ramodels-50.3.0.dist-info/METADATA
ramodels-50.3.0.dist-info/RECORD
