Metadata-Version: 2.1
Name: ramodels
Version: 50.3.0
Summary: Pydantic data models for OS2mo
Home-page: https://magenta.dk/
License: MPL-2.0
Keywords: os2mo,data models
Author: Magenta
Author-email: info@magenta.dk
Requires-Python: >=3.11,<4.0
Classifier: License :: OSI Approved
Classifier: Programming Language :: Python :: 3
Classifier: Programming Language :: Python :: 3.11
Requires-Dist: mkdocstrings[python] (>=0.19.0,<0.20.0)
Requires-Dist: more-itertools (>=9.0.0,<10.0.0)
Requires-Dist: pydantic (>=1.10.2,<2.0.0)
Requires-Dist: python-dateutil (>=2.8.2,<3.0.0)
Project-URL: Repository, https://git.magenta.dk/rammearkitektur/os2mo
